mwc/__init__.py
mwc/cli.py
mwc/counter.py
markdown_word_count-0.1.0.dist-info/LICENSE
markdown_word_count-0.1.0.dist-info/METADATA
markdown_word_count-0.1.0.dist-info/WHEEL
markdown_word_count-0.1.0.dist-info/entry_points.txt
markdown_word_count-0.1.0.dist-info/top_level.txt
markdown_word_count-0.1.0.dist-info/RECORD
