Metadata-Version: 2.1
Name: markdown-word-count
Version: 0.1.0
Summary: Word counter for raw Markdown files
Home-page: https://github.com/gandreadis/markdown-word-count
Author: Georgios Andreadis
Author-email: info@gandreadis.com
Classifier: Programming Language :: Python :: 3
Classifier: License :: OSI Approved :: MIT License
Classifier: Operating System :: OS Independent
Requires-Python: >=3.6
License-File: LICENSE
